MANIFEST.in
setup.py
pachi_py/Makefile
pachi_py/__init__.py
pachi_py/cypachi.cpp
pachi_py/cypachi.h
pachi_py/cypachi.pyx
pachi_py/exceptions.hpp
pachi_py/extra_unused.pyx
pachi_py/goutil.cpp
pachi_py/goutil.hpp
pachi_py/ptr.hpp
pachi_py.egg-info/PKG-INFO
pachi_py.egg-info/SOURCES.txt
pachi_py.egg-info/dependency_links.txt
pachi_py.egg-info/requires.txt
pachi_py.egg-info/top_level.txt
pachi_py/pachi/.gitignore
pachi_py/pachi/ANDROID.txt
pachi_py/pachi/CMakeLists.txt
pachi_py/pachi/COPYING
pachi_py/pachi/CREDITS
pachi_py/pachi/HACKING
pachi_py/pachi/Makefile
pachi_py/pachi/Makefile.lib
pachi_py/pachi/README
pachi_py/pachi/TODO
pachi_py/pachi/board.c
pachi_py/pachi/board.h
pachi_py/pachi/book.dat.bad
pachi_py/pachi/book.dat.extra
pachi_py/pachi/chat.c
pachi_py/pachi/chat.h
pachi_py/pachi/dcnn.cpp
pachi_py/pachi/dcnn.h
pachi_py/pachi/debug.h
pachi_py/pachi/engine.h
pachi_py/pachi/fbook.c
pachi_py/pachi/fbook.h
pachi_py/pachi/fixp.h
pachi_py/pachi/gogui.h
pachi_py/pachi/gtp.c
pachi_py/pachi/gtp.h
pachi_py/pachi/joseki19.pdict
pachi_py/pachi/libpachi_globals.c
pachi_py/pachi/move.c
pachi_py/pachi/move.h
pachi_py/pachi/mq.h
pachi_py/pachi/network.c
pachi_py/pachi/network.h
pachi_py/pachi/ownermap.c
pachi_py/pachi/ownermap.h
pachi_py/pachi/pachi.c
pachi_py/pachi/pattern.c
pachi_py/pachi/pattern.h
pachi_py/pachi/pattern3.c
pachi_py/pachi/pattern3.h
pachi_py/pachi/patternprob.c
pachi_py/pachi/patternprob.h
pachi_py/pachi/patternsp.c
pachi_py/pachi/patternsp.h
pachi_py/pachi/playout.c
pachi_py/pachi/playout.h
pachi_py/pachi/probdist.c
pachi_py/pachi/probdist.h
pachi_py/pachi/random.c
pachi_py/pachi/random.h
pachi_py/pachi/stats.h
pachi_py/pachi/stone.c
pachi_py/pachi/stone.h
pachi_py/pachi/timeinfo.c
pachi_py/pachi/timeinfo.h
pachi_py/pachi/util.h
pachi_py/pachi/version.h
pachi_py/pachi/distributed/Makefile
pachi_py/pachi/distributed/distributed.c
pachi_py/pachi/distributed/distributed.h
pachi_py/pachi/distributed/merge.c
pachi_py/pachi/distributed/merge.h
pachi_py/pachi/distributed/protocol.c
pachi_py/pachi/distributed/protocol.h
pachi_py/pachi/joseki/Makefile
pachi_py/pachi/joseki/README
pachi_py/pachi/joseki/base.c
