Metadata-Version: 1.1
Name: pachi-py
Version: 0.0.21
Summary: Python bindings to Pachi
Home-page: https://github.com/openai/pachi-py
Author: OpenAI
Author-email: info@openai.com
License: UNKNOWN
Platform: UNKNOWN
Classifier: License :: OSI Approved :: GNU General Public License v2 (GPLv2)
